trengo/__init__.py
trengo/py.typed
pytrengo-0.1.4.dist-info/LICENSE
pytrengo-0.1.4.dist-info/METADATA
pytrengo-0.1.4.dist-info/WHEEL
pytrengo-0.1.4.dist-info/RECORD
