Metadata-Version: 2.1
Name: pytrengo
Version: 0.1.4
Summary: Python client for the Trengo REST API.
Keywords: trengo,pytrengo
Author: Baptiste Fontaine
Author-email: baptiste@bixoto.com
Requires-Python: >=3.10,<4.0
Classifier: Development Status :: 4 - Beta
Classifier: License :: OSI Approved :: MIT License
Classifier: Programming Language :: Python :: 3
Classifier: Programming Language :: Python :: 3.10
Classifier: Programming Language :: Python :: 3.11
Classifier: Programming Language :: Python :: 3.12
Requires-Dist: api-session (>=1.4.1,<2.0.0)
